{
	"info": {
		"_postman_id": "6948900e-960c-43ac-a927-8c94c80a2415",
		"name": "week1.day2",
		"schema": "https://schema.getpostman.com/json/collection/v2.1.0/collection.json",
		"_exporter_id": "28447185",
		"_collection_link": "https://testleaf-4289.postman.co/workspace/REST_API_Session_Jun_2025~c55ec55d-358e-4b2e-96dc-a16d8089d6de/collection/28447185-6948900e-960c-43ac-a927-8c94c80a2415?action=share&source=collection_link&creator=28447185"
	},
	"item": [
		{
			"name": "Retrieve_records_from_a_incident_table",
			"request": {
				"auth": {
					"type": "basic",
					"basic": [
						{
							"key": "password",
							"value": "d@9IvhOh5DR*",
							"type": "string"
						},
						{
							"key": "username",
							"value": "admin",
							"type": "string"
						}
					]
				},
				"method": "GET",
				"header": [],
				"url": {
					"raw": "https://dev265761.service-now.com/api/now/table/:tableName",
					"protocol": "https",
					"host": [
						"dev265761",
						"service-now",
						"com"
					],
					"path": [
						"api",
						"now",
						"table",
						":tableName"
					],
					"variable": [
						{
							"key": "tableName",
							"value": "incident"
						}
					]
				}
			},
			"response": []
		},
		{
			"name": "Retrieve_records_from_a_incident_table_response_as_xml",
			"protocolProfileBehavior": {
				"disabledSystemHeaders": {
					"accept": true
				}
			},
			"request": {
				"auth": {
					"type": "basic",
					"basic": [
						{
							"key": "password",
							"value": "d@9IvhOh5DR*",
							"type": "string"
						},
						{
							"key": "username",
							"value": "admin",
							"type": "string"
						}
					]
				},
				"method": "GET",
				"header": [
					{
						"key": "Accept",
						"value": "application/xml",
						"type": "text"
					},
					{
						"key": "Content-Type",
						"value": "application/json",
						"type": "text"
					}
				],
				"url": {
					"raw": "https://dev265761.service-now.com/api/now/table/:tableName",
					"protocol": "https",
					"host": [
						"dev265761",
						"service-now",
						"com"
					],
					"path": [
						"api",
						"now",
						"table",
						":tableName"
					],
					"variable": [
						{
							"key": "tableName",
							"value": "incident"
						}
					]
				}
			},
			"response": []
		}
	]
}